README.rst
setup.py
cities_teryt/__init__.py
cities_teryt/admin.py
cities_teryt/models.py
cities_teryt/settings.py
cities_teryt/tests.py
cities_teryt/views.py
cities_teryt/management/__init__.py
cities_teryt/management/commands/__init__.py
cities_teryt/management/commands/cities_teryt.py
django_cities_teryt.egg-info/PKG-INFO
django_cities_teryt.egg-info/SOURCES.txt
django_cities_teryt.egg-info/dependency_links.txt
django_cities_teryt.egg-info/not-zip-safe
django_cities_teryt.egg-info/requires.txt
django_cities_teryt.egg-info/top_level.txt