Metadata-Version: 1.1
Name: django-cities-teryt
Version: 1.0.0
Summary: Polish region and city data for Django.
Home-page: https://github.com/lukaszbanasiak/django-cities-teryt
Author: Łukasz Banasiak
Author-email: lukas.banasiak@gmail.com
License: MIT
Keywords: django cities teryt gus provinces counties municipalities villages districts
Platform: UNKNOWN
Classifier: Development Status :: 5 - Production/Stable
Classifier: Environment :: Web Environment
Classifier: Framework :: Django
Classifier: Intended Audience :: Developers
Classifier: License :: OSI Approved :: MIT License
Classifier: Operating System :: OS Independent
Classifier: Programming Language :: Python
Classifier: Programming Language :: Python :: 2
Classifier: Topic :: Internet :: WWW/HTTP
Classifier: Topic :: Software Development :: Libraries :: Python Modules
